{
  "gameObjects": [
    {
      "id": "clks1i8we0000d79s69pndu41",
      "name": "cake",
      "description": "",
      "tagIds": []
    },
    {
      "id": "clks1i8we0001d79s7asfdtvu",
      "name": "chocolate",
      "description": "",
      "tagIds": []
    },
    {
      "id": "clks1i8we0002d79s6uw66pvs",
      "name": "ice cream",
      "description": "",
      "tagIds": []
    },
    {
      "id": "clks1i8we0003d79samrqec23",
      "name": "fruit salad",
      "description": "",
      "tagIds": []
    },
    {
      "id": "clks1i8we0004d79s8ubyfsm4",
      "name": "potato chips",
      "description": "",
      "tagIds": []
    },
    {
      "id": "clks1i8we0005d79shcswhsz9",
      "name": "pretzels",
      "description": "",
      "tagIds": []
    },
    {
      "id": "clks1i8we0006d79s00e39np4",
      "name": "popcorn",
      "description": "",
      "tagIds": []
    },
    {
      "id": "clks1i8we0007d79selfrgzvi",
      "name": "french fries",
      "description": "",
      "tagIds": []
    },
    {
      "id": "clks1i8we0008d79s1ndrc1bw",
      "name": "curry",
      "description": "",
      "tagIds": []
    },
    {
      "id": "clks1i8we0009d79s2x3363zw",
      "name": "salsa",
      "description": "",
      "tagIds": []
    },
    {
      "id": "clks1i8we000ad79s2or7695b",
      "name": "hot wings",
      "description": "",
      "tagIds": []
    },
    {
      "id": "clks1i8we000bd79s165edc7k",
      "name": "kimchi",
      "description": "",
      "tagIds": []
    },
    {
      "id": "clks1i8we000cd79sh1f7glj5",
      "name": "lemon",
      "description": "",
      "tagIds": []
    },
    {
      "id": "clks1i8we000dd79s9kc93yzy",
      "name": "vinegar",
      "description": "",
      "tagIds": []
    },
    {
      "id": "clks1i8we000ed79scukv63q8",
      "name": "pickles",
      "description": "",
      "tagIds": []
    },
    {
      "id": "clks1i8we000fd79s9n1na7bv",
      "name": "yogurt",
      "description": "",
      "tagIds": []
    },
    {
      "id": "clks1i8we000gd79sdrov7rdw",
      "name": "coffee",
      "description": "",
      "tagIds": []
    },
    {
      "id": "clks1i8we000hd79sgy8t4nel",
      "name": "dark chocolate",
      "description": "",
      "tagIds": []
    },
    {
      "id": "clks1i8we000id79s35cb0zuk",
      "name": "kale",
      "description": "",
      "tagIds": []
    },
    {
      "id": "clks1i8we000jd79seu4v94t8",
      "name": "grapefruit",
      "description": "",
      "tagIds": []
    },
    {
      "id": "clks1i8we000kd79sezax7pcq",
      "name": "soy sauce",
      "description": "",
      "tagIds": []
    },
    {
      "id": "clks1i8we000ld79sb64d2hvs",
      "name": "mushrooms",
      "description": "",
      "tagIds": []
    },
    {
      "id": "clks1i8we000md79s1kdu5tj2",
      "name": "beef broth",
      "description": "",
      "tagIds": []
    },
    {
      "id": "clks1i8we000nd79shl63dgpn",
      "name": "Parmesan cheese",
      "description": "",
      "tagIds": []
    },
    {
      "id": "clks1i8we000od79scmjdb8sj",
      "name": "scrambled eggs",
      "description": "",
      "tagIds": []
    },
    {
      "id": "clks1i8we000pd79s2flz1cbk",
      "name": "bacon",
      "description": "",
      "tagIds": []
    },
    {
      "id": "clks1i8we000qd79scipzb0lp",
      "name": "pancakes",
      "description": "",
      "tagIds": []
    },
    {
      "id": "clks1i8we000rd79sen857ecc",
      "name": "oatmeal",
      "description": "",
      "tagIds": []
    },
    {
      "id": "clks1i8we000sd79sgjevg1sn",
      "name": "sandwich",
      "description": "",
      "tagIds": []
    },
    {
      "id": "clks1i8we000td79s9ucfa1fd",
      "name": "salad",
      "description": "",
      "tagIds": []
    },
    {
      "id": "clks1i8we000ud79sccxo7o54",
      "name": "soup",
      "description": "",
      "tagIds": []
    },
    {
      "id": "clks1i8wf000vd79safifcwpf",
      "name": "pizza",
      "description": "",
      "tagIds": []
    },
    {
      "id": "clks1i8wf000wd79s6o296g6o",
      "name": "steak",
      "description": "",
      "tagIds": []
    },
    {
      "id": "clks1i8wf000xd79sd73rgiys",
      "name": "grilled chicken",
      "description": "",
      "tagIds": []
    },
    {
      "id": "clks1i8wf000yd79sccq4hhel",
      "name": "pasta",
      "description": "",
      "tagIds": []
    },
    {
      "id": "clks1i8wf000zd79sgtpr2rlp",
      "name": "sushi",
      "description": "",
      "tagIds": []
    },
    {
      "id": "clks1i8wf0010d79s3dqc4fme",
      "name": "chips",
      "description": "",
      "tagIds": []
    },
    {
      "id": "clks1i8wf0011d79s2wqt0sbc",
      "name": "nuts",
      "description": "",
      "tagIds": []
    },
    {
      "id": "clks1i8wf0012d79s8v832c3b",
      "name": "fruit",
      "description": "",
      "tagIds": []
    },
    {
      "id": "clks1i8wf0013d79s8l0z84v5",
      "name": "yogurt",
      "description": "",
      "tagIds": []
    },
    {
      "id": "clks1i8wf0014d79sd6hl3uuy",
      "name": "cake",
      "description": "",
      "tagIds": []
    },
    {
      "id": "clks1i8wf0015d79sbqoqhzac",
      "name": "ice cream",
      "description": "",
      "tagIds": []
    },
    {
      "id": "clks1i8wf0016d79sabof447m",
      "name": "cookies",
      "description": "",
      "tagIds": []
    },
    {
      "id": "clks1i8wf0017d79s343taa32",
      "name": "pie",
      "description": "",
      "tagIds": []
    }
  ],
  "tags": [
    {
      "id": "",
      "name": "",
      "description": ""
    }
  ]
}